configtony/__init__.py
configtony/config.py
configtony-1.0.0.dist-info/licenses/LICENSE
configtony-1.0.0.dist-info/METADATA
configtony-1.0.0.dist-info/WHEEL
configtony-1.0.0.dist-info/top_level.txt
configtony-1.0.0.dist-info/RECORD
